pypacktest/__init__.py
pypacktest-0.1.dist-info/LICENSE
pypacktest-0.1.dist-info/METADATA
pypacktest-0.1.dist-info/WHEEL
pypacktest-0.1.dist-info/top_level.txt
pypacktest-0.1.dist-info/RECORD
