Metadata-Version: 2.1
Name: pypacktest
Version: 0.1
Summary: Python Package test
Home-page: https://github.com/achabrier/pypacktest
Author: Alain Chabrier
Author-email: alain.chabrier@ibm.com
License: UNKNOWN
Platform: UNKNOWN
Classifier: Programming Language :: Python :: 3
Classifier: License :: OSI Approved :: MIT License
Classifier: Operating System :: OS Independent
